{"ticker": "AG", "signalDate": "2024-04-03", "signalIndex": 20, "bars": [{"date": "2024-03-05", "open": 5.05, "high": 5.1, "low": 4.85, "close": 4.915, "volume": 741639, "ema20": 4.6828, "sma50": 5.0284, "sma200": 5.5371}, {"date": "2024-03-06", "open": 5.05, "high": 5.17, "low": 5.02, "close": 5.1, "volume": 538195, "ema20": 4.7225, "sma50": 5.004, "sma200": 5.5317}, {"date": "2024-03-07", "open": 5.17, "high": 5.33, "low": 5.1, "close": 5.315, "volume": 544678, "ema20": 4.7789, "sma50": 4.9849, "sma200": 5.5273}, {"date": "2024-03-08", "open": 5.35, "high": 5.4, "low": 5.21, "close": 5.3, "volume": 610768, "ema20": 4.8286, "sma50": 4.9631, "sma200": 5.5232}, {"date": "2024-03-11", "open": 5.34, "high": 5.535, "low": 5.25, "close": 5.47, "volume": 632497, "ema20": 4.8897, "sma50": 4.9439, "sma200": 5.5199}, {"date": "2024-03-12", "open": 5.4, "high": 5.4, "low": 5.2, "close": 5.39, "volume": 568627, "ema20": 4.9373, "sma50": 4.9277, "sma200": 5.5171}, {"date": "2024-03-13", "open": 5.39, "high": 5.595, "low": 5.315, "close": 5.485, "volume": 632283, "ema20": 4.9895, "sma50": 4.9145, "sma200": 5.5157}, {"date": "2024-03-14", "open": 5.42, "high": 5.465, "low": 5.335, "close": 5.4, "volume": 606011, "ema20": 5.0286, "sma50": 4.9025, "sma200": 5.514}, {"date": "2024-03-15", "open": 5.43, "high": 5.65, "low": 5.38, "close": 5.64, "volume": 644420, "ema20": 5.0868, "sma50": 4.9043, "sma200": 5.5136}, {"date": "2024-03-18", "open": 5.625, "high": 5.65, "low": 5.525, "close": 5.57, "volume": 906169, "ema20": 5.1328, "sma50": 4.9033, "sma200": 5.5124}, {"date": "2024-03-19", "open": 5.48, "high": 5.5, "low": 5.24, "close": 5.255, "volume": 613766, "ema20": 5.1445, "sma50": 4.8968, "sma200": 5.5086}, {"date": "2024-03-20", "open": 5.24, "high": 5.65, "low": 5.22, "close": 5.575, "volume": 768555, "ema20": 5.1855, "sma50": 4.8981, "sma200": 5.5069}, {"date": "2024-03-21", "open": 5.68, "high": 5.8, "low": 5.43, "close": 5.43, "volume": 1027688, "ema20": 5.2087, "sma50": 4.8975, "sma200": 5.5047}, {"date": "2024-03-22", "open": 5.39, "high": 5.48, "low": 5.305, "close": 5.34, "volume": 412424, "ema20": 5.2212, "sma50": 4.8943, "sma200": 5.5021}, {"date": "2024-03-25", "open": 5.38, "high": 5.54, "low": 5.3, "close": 5.325, "volume": 598837, "ema20": 5.2311, "sma50": 4.8944, "sma200": 5.4999}, {"date": "2024-03-26", "open": 5.44, "high": 5.5, "low": 5.25, "close": 5.25, "volume": 614691, "ema20": 5.2329, "sma50": 4.8872, "sma200": 5.4968}, {"date": "2024-03-27", "open": 5.32, "high": 5.6, "low": 5.27, "close": 5.6, "volume": 538208, "ema20": 5.2679, "sma50": 4.8983, "sma200": 5.4961}, {"date": "2024-03-28", "open": 5.66, "high": 5.93, "low": 5.57, "close": 5.91, "volume": 678760, "ema20": 5.329, "sma50": 4.9213, "sma200": 5.4972}, {"date": "2024-04-01", "open": 6.0, "high": 6.28, "low": 5.99, "close": 6.225, "volume": 845207, "ema20": 5.4144, "sma50": 4.9527, "sma200": 5.5002}, {"date": "2024-04-02", "open": 6.32, "high": 6.48, "low": 6.205, "close": 6.48, "volume": 1196828, "ema20": 5.5159, "sma50": 4.9879, "sma200": 5.5047}, {"date": "2024-04-03", "open": 6.45, "high": 7.65, "low": 6.45, "close": 7.65, "volume": 2157892, "ema20": 5.7191, "sma50": 5.0434, "sma200": 5.515}, {"date": "2024-04-04", "open": 7.46, "high": 7.71, "low": 7.29, "close": 7.54, "volume": 1856714, "ema20": 5.8925, "sma50": 5.0953, "sma200": 5.5249}, {"date": "2024-04-05", "open": 7.57, "high": 7.875, "low": 7.37, "close": 7.79, "volume": 1111846, "ema20": 6.0732, "sma50": 5.1551, "sma200": 5.5367}, {"date": "2024-04-08", "open": 8.05, "high": 8.19, "low": 7.65, "close": 8.0, "volume": 1130037, "ema20": 6.2567, "sma50": 5.2177, "sma200": 5.55}, {"date": "2024-04-09", "open": 8.14, "high": 8.335, "low": 8.01, "close": 8.06, "volume": 1032352, "ema20": 6.4285, "sma50": 5.2817, "sma200": 5.5637}, {"date": "2024-04-10", "open": 8.07, "high": 8.295, "low": 7.51, "close": 7.95, "volume": 973071, "ema20": 6.5734, "sma50": 5.3485, "sma200": 5.5768}, {"date": "2024-04-11", "open": 8.0, "high": 8.12, "low": 7.7, "close": 7.97, "volume": 563485, "ema20": 6.7064, "sma50": 5.4159, "sma200": 5.5892}, {"date": "2024-04-12", "open": 8.22, "high": 8.42, "low": 7.395, "close": 7.5, "volume": 1615919, "ema20": 6.782, "sma50": 5.4734, "sma200": 5.5995}, {"date": "2024-04-15", "open": 7.69, "high": 7.82, "low": 7.34, "close": 7.45, "volume": 817971, "ema20": 6.8456, "sma50": 5.5241, "sma200": 5.6098}, {"date": "2024-04-16", "open": 7.18, "high": 7.18, "low": 6.71, "close": 6.72, "volume": 1318114, "ema20": 6.8336, "sma50": 5.5624, "sma200": 5.6162}, {"date": "2024-04-17", "open": 6.95, "high": 7.11, "low": 6.77, "close": 6.84, "volume": 556732, "ema20": 6.8342, "sma50": 5.6068, "sma200": 5.6222}, {"date": "2024-04-18", "open": 6.96, "high": 7.08, "low": 6.745, "close": 6.77, "volume": 488442, "ema20": 6.8281, "sma50": 5.6476, "sma200": 5.6272}, {"date": "2024-04-19", "open": 6.73, "high": 6.99, "low": 6.68, "close": 6.68, "volume": 814074, "ema20": 6.814, "sma50": 5.6878, "sma200": 5.6322}, {"date": "2024-04-22", "open": 6.5, "high": 6.67, "low": 6.185, "close": 6.55, "volume": 747364, "ema20": 6.7889, "sma50": 5.7257, "sma200": 5.6374}, {"date": "2024-04-23", "open": 6.42, "high": 6.885, "low": 6.4, "close": 6.82, "volume": 611282, "ema20": 6.7918, "sma50": 5.7704, "sma200": 5.6436}, {"date": "2024-04-24", "open": 6.69, "high": 6.87, "low": 6.69, "close": 6.805, "volume": 347409, "ema20": 6.7931, "sma50": 5.8147, "sma200": 5.6485}, {"date": "2024-04-25", "open": 6.91, "high": 7.01, "low": 6.655, "close": 6.935, "volume": 612186, "ema20": 6.8066, "sma50": 5.8691, "sma200": 5.654}, {"date": "2024-04-26", "open": 7.07, "high": 7.14, "low": 6.74, "close": 6.98, "volume": 595522, "ema20": 6.8231, "sma50": 5.9227, "sma200": 5.6569}, {"date": "2024-04-29", "open": 7.04, "high": 7.13, "low": 6.79, "close": 6.85, "volume": 384938, "ema20": 6.8257, "sma50": 5.9692, "sma200": 5.659}, {"date": "2024-04-30", "open": 6.63, "high": 6.82, "low": 6.49, "close": 6.67, "volume": 314771, "ema20": 6.8109, "sma50": 6.0114, "sma200": 5.6597}, {"date": "2024-05-01", "open": 6.73, "high": 7.005, "low": 6.625, "close": 6.72, "volume": 489229, "ema20": 6.8022, "sma50": 6.0552, "sma200": 5.66}, {"date": "2024-05-02", "open": 6.61, "high": 6.81, "low": 6.59, "close": 6.72, "volume": 310369, "ema20": 6.7944, "sma50": 6.1, "sma200": 5.659}, {"date": "2024-05-03", "open": 6.82, "high": 6.92, "low": 6.61, "close": 6.71, "volume": 376032, "ema20": 6.7863, "sma50": 6.1424, "sma200": 5.6577}, {"date": "2024-05-06", "open": 6.88, "high": 7.27, "low": 6.88, "close": 7.1, "volume": 713294, "ema20": 6.8162, "sma50": 6.1912, "sma200": 5.6591}, {"date": "2024-05-07", "open": 7.09, "high": 7.41, "low": 7.08, "close": 7.29, "volume": 689333, "ema20": 6.8613, "sma50": 6.2449, "sma200": 5.6614}, {"date": "2024-05-08", "open": 7.19, "high": 7.235, "low": 6.94, "close": 7.06, "volume": 567379, "ema20": 6.8803, "sma50": 6.2945, "sma200": 5.6636}, {"date": "2024-05-09", "open": 7.15, "high": 7.66, "low": 7.15, "close": 7.485, "volume": 758214, "ema20": 6.9378, "sma50": 6.3558, "sma200": 5.6675}, {"date": "2024-05-10", "open": 7.68, "high": 7.68, "low": 7.26, "close": 7.3, "volume": 494115, "ema20": 6.9723, "sma50": 6.4119, "sma200": 5.6701}, {"date": "2024-05-13", "open": 7.27, "high": 7.37, "low": 7.03, "close": 7.13, "volume": 411163, "ema20": 6.9874, "sma50": 6.46, "sma200": 5.6743}, {"date": "2024-05-14", "open": 7.25, "high": 7.32, "low": 7.04, "close": 7.28, "volume": 505886, "ema20": 7.0152, "sma50": 6.506, "sma200": 5.6788}, {"date": "2024-05-15", "open": 7.23, "high": 7.57, "low": 7.16, "close": 7.52, "volume": 636869, "ema20": 7.0633, "sma50": 6.5581, "sma200": 5.683}, {"date": "2024-05-16", "open": 7.43, "high": 7.465, "low": 7.265, "close": 7.42, "volume": 410568, "ema20": 7.0973, "sma50": 6.6045, "sma200": 5.6881}, {"date": "2024-05-17", "open": 7.68, "high": 8.07, "low": 7.4, "close": 8.07, "volume": 1375034, "ema20": 7.1899, "sma50": 6.6596, "sma200": 5.6976}, {"date": "2024-05-20", "open": 8.21, "high": 8.21, "low": 7.76, "close": 7.98, "volume": 817014, "ema20": 7.2652, "sma50": 6.7132, "sma200": 5.7078}, {"date": "2024-05-21", "open": 7.9, "high": 7.94, "low": 7.55, "close": 7.62, "volume": 763189, "ema20": 7.299, "sma50": 6.7562, "sma200": 5.7156}, {"date": "2024-05-22", "open": 7.65, "high": 7.65, "low": 7.17, "close": 7.24, "volume": 537432, "ema20": 7.2933, "sma50": 6.7932, "sma200": 5.7219}, {"date": "2024-05-23", "open": 7.17, "high": 7.31, "low": 7.0, "close": 7.03, "volume": 624331, "ema20": 7.2683, "sma50": 6.8241, "sma200": 5.7271}, {"date": "2024-05-24", "open": 7.17, "high": 7.26, "low": 7.055, "close": 7.18, "volume": 387802, "ema20": 7.2599, "sma50": 6.8597, "sma200": 5.733}, {"date": "2024-05-28", "open": 7.5, "high": 7.655, "low": 7.355, "close": 7.57, "volume": 432189, "ema20": 7.2894, "sma50": 6.8983, "sma200": 5.7404}, {"date": "2024-05-29", "open": 7.49, "high": 7.5, "low": 7.26, "close": 7.26, "volume": 241407, "ema20": 7.2866, "sma50": 6.9321, "sma200": 5.7447}, {"date": "2024-05-30", "open": 7.22, "high": 7.46, "low": 7.165, "close": 7.19, "volume": 388211, "ema20": 7.2774, "sma50": 6.9708, "sma200": 5.75}, {"date": "2024-05-31", "open": 7.34, "high": 7.44, "low": 7.12, "close": 7.165, "volume": 295838, "ema20": 7.2667, "sma50": 7.0026, "sma200": 5.7564}, {"date": "2024-06-03", "open": 7.17, "high": 7.22, "low": 7.04, "close": 7.095, "volume": 321314, "ema20": 7.2503, "sma50": 7.0359, "sma200": 5.7628}, {"date": "2024-06-04", "open": 6.85, "high": 6.96, "low": 6.625, "close": 6.65, "volume": 482104, "ema20": 7.1932, "sma50": 7.0621, "sma200": 5.7668}, {"date": "2024-06-05", "open": 6.72, "high": 6.75, "low": 6.515, "close": 6.715, "volume": 649247, "ema20": 7.1476, "sma50": 7.0899, "sma200": 5.7711}, {"date": "2024-06-06", "open": 6.79, "high": 6.935, "low": 6.68, "close": 6.85, "volume": 402722, "ema20": 7.1193, "sma50": 7.1219, "sma200": 5.7759}, {"date": "2024-06-07", "open": 6.61, "high": 6.61, "low": 6.265, "close": 6.33, "volume": 577695, "ema20": 7.0441, "sma50": 7.1365, "sma200": 5.7778}, {"date": "2024-06-10", "open": 6.36, "high": 6.385, "low": 6.14, "close": 6.37, "volume": 452888, "ema20": 6.9799, "sma50": 7.1457, "sma200": 5.7794}, {"date": "2024-06-11", "open": 6.29, "high": 6.375, "low": 6.16, "close": 6.345, "volume": 297344, "ema20": 6.9194, "sma50": 7.1481, "sma200": 5.7812}, {"date": "2024-06-12", "open": 6.5, "high": 6.66, "low": 6.11, "close": 6.17, "volume": 398120, "ema20": 6.8481, "sma50": 7.1419, "sma200": 5.7824}, {"date": "2024-06-13", "open": 6.09, "high": 6.26, "low": 5.97, "close": 6.09, "volume": 479531, "ema20": 6.7759, "sma50": 7.1107, "sma200": 5.7821}]}