{"ticker": "GME", "signalDate": "2024-05-13", "signalIndex": 30, "bars": [{"date": "2024-04-01", "open": 12.6, "high": 12.67, "low": 11.54, "close": 12.05, "volume": 665300, "ema20": 13.7415, "sma50": 14.1821, "sma200": 16.8358}, {"date": "2024-04-02", "open": 11.94, "high": 11.985, "low": 11.26, "close": 11.3, "volume": 464979, "ema20": 13.509, "sma50": 14.1177, "sma200": 16.764}, {"date": "2024-04-03", "open": 11.34, "high": 11.49, "low": 10.91, "close": 11.44, "volume": 326309, "ema20": 13.3119, "sma50": 14.0497, "sma200": 16.6973}, {"date": "2024-04-04", "open": 11.46, "high": 11.82, "low": 11.3, "close": 11.48, "volume": 565420, "ema20": 13.1375, "sma50": 13.9956, "sma200": 16.6317}, {"date": "2024-04-05", "open": 11.53, "high": 11.58, "low": 10.98, "close": 11.25, "volume": 601977, "ema20": 12.9577, "sma50": 13.943, "sma200": 16.5651}, {"date": "2024-04-08", "open": 11.28, "high": 11.36, "low": 10.84, "close": 10.89, "volume": 288197, "ema20": 12.7608, "sma50": 13.8718, "sma200": 16.4979}, {"date": "2024-04-09", "open": 10.85, "high": 11.25, "low": 10.72, "close": 11.15, "volume": 299669, "ema20": 12.6074, "sma50": 13.806, "sma200": 16.432}, {"date": "2024-04-10", "open": 11.01, "high": 11.06, "low": 10.755, "close": 10.85, "volume": 303648, "ema20": 12.44, "sma50": 13.7276, "sma200": 16.368}, {"date": "2024-04-11", "open": 10.86, "high": 11.385, "low": 10.805, "close": 11.29, "volume": 382062, "ema20": 12.3305, "sma50": 13.6634, "sma200": 16.3094}, {"date": "2024-04-12", "open": 11.22, "high": 11.22, "low": 10.76, "close": 10.8, "volume": 264384, "ema20": 12.1847, "sma50": 13.595, "sma200": 16.2456}, {"date": "2024-04-15", "open": 10.85, "high": 10.9, "low": 10.05, "close": 10.05, "volume": 375581, "ema20": 11.9814, "sma50": 13.5072, "sma200": 16.1709}, {"date": "2024-04-16", "open": 10.06, "high": 10.45, "low": 9.95, "close": 10.38, "volume": 325717, "ema20": 11.8289, "sma50": 13.421, "sma200": 16.0978}, {"date": "2024-04-17", "open": 10.4, "high": 10.58, "low": 10.3, "close": 10.32, "volume": 174384, "ema20": 11.6852, "sma50": 13.3574, "sma200": 16.0277}, {"date": "2024-04-18", "open": 10.35, "high": 10.62, "low": 10.27, "close": 10.33, "volume": 193175, "ema20": 11.5561, "sma50": 13.2822, "sma200": 15.9547}, {"date": "2024-04-19", "open": 10.28, "high": 10.495, "low": 10.21, "close": 10.41, "volume": 231758, "ema20": 11.447, "sma50": 13.2092, "sma200": 15.8872}, {"date": "2024-04-22", "open": 10.46, "high": 10.46, "low": 10.0, "close": 10.0, "volume": 216612, "ema20": 11.3092, "sma50": 13.1224, "sma200": 15.823}, {"date": "2024-04-23", "open": 10.09, "high": 10.28, "low": 10.015, "close": 10.17, "volume": 210374, "ema20": 11.2007, "sma50": 13.0324, "sma200": 15.7604}, {"date": "2024-04-24", "open": 10.24, "high": 10.94, "low": 10.16, "close": 10.75, "volume": 352976, "ema20": 11.1578, "sma50": 12.953, "sma200": 15.6965}, {"date": "2024-04-25", "open": 10.95, "high": 11.24, "low": 10.49, "close": 11.11, "volume": 341206, "ema20": 11.1532, "sma50": 12.8918, "sma200": 15.6321}, {"date": "2024-04-26", "open": 11.19, "high": 12.18, "low": 11.02, "close": 11.76, "volume": 574650, "ema20": 11.211, "sma50": 12.8384, "sma200": 15.5735}, {"date": "2024-04-29", "open": 11.89, "high": 11.97, "low": 11.18, "close": 11.26, "volume": 248501, "ema20": 11.2157, "sma50": 12.7738, "sma200": 15.5125}, {"date": "2024-04-30", "open": 11.32, "high": 11.32, "low": 10.91, "close": 11.09, "volume": 117165, "ema20": 11.2037, "sma50": 12.7132, "sma200": 15.4531}, {"date": "2024-05-01", "open": 11.0, "high": 11.32, "low": 10.7, "close": 11.03, "volume": 131082, "ema20": 11.1872, "sma50": 12.6642, "sma200": 15.3942}, {"date": "2024-05-02", "open": 11.11, "high": 12.875, "low": 10.96, "close": 12.58, "volume": 455972, "ema20": 11.3198, "sma50": 12.6478, "sma200": 15.342}, {"date": "2024-05-03", "open": 12.5, "high": 17.44, "low": 12.35, "close": 16.1, "volume": 1994134, "ema20": 11.7751, "sma50": 12.7026, "sma200": 15.3076}, {"date": "2024-05-06", "open": 16.1, "high": 17.37, "low": 13.625, "close": 16.0, "volume": 3559174, "ema20": 12.1774, "sma50": 12.7522, "sma200": 15.2732}, {"date": "2024-05-07", "open": 15.77, "high": 17.29, "low": 14.94, "close": 16.05, "volume": 975255, "ema20": 12.5463, "sma50": 12.7998, "sma200": 15.2391}, {"date": "2024-05-08", "open": 15.88, "high": 17.23, "low": 15.34, "close": 15.95, "volume": 1203724, "ema20": 12.8704, "sma50": 12.8258, "sma200": 15.204}, {"date": "2024-05-09", "open": 15.95, "high": 18.57, "low": 15.35, "close": 18.57, "volume": 1264463, "ema20": 13.4132, "sma50": 12.9162, "sma200": 15.1826}, {"date": "2024-05-10", "open": 18.3, "high": 20.19, "low": 16.88, "close": 17.35, "volume": 2171266, "ema20": 13.7882, "sma50": 12.978, "sma200": 15.1557}, {"date": "2024-05-13", "open": 21.73, "high": 38.2, "low": 21.15, "close": 36.91, "volume": 6270564, "ema20": 15.9902, "sma50": 13.4182, "sma200": 15.2302}, {"date": "2024-05-14", "open": 47.75, "high": 80.0, "low": 36.0, "close": 51.0, "volume": 8156894, "ema20": 19.3245, "sma50": 14.1336, "sma200": 15.3754}, {"date": "2024-05-15", "open": 50.98, "high": 53.15, "low": 31.0, "close": 35.89, "volume": 4143945, "ema20": 20.9022, "sma50": 14.5508, "sma200": 15.4439}, {"date": "2024-05-16", "open": 33.75, "high": 37.31, "low": 26.17, "close": 28.69, "volume": 3026699, "ema20": 21.6439, "sma50": 14.82, "sma200": 15.4798}, {"date": "2024-05-17", "open": 29.84, "high": 29.88, "low": 19.7, "close": 21.16, "volume": 4592121, "ema20": 21.5978, "sma50": 14.938, "sma200": 15.4813}, {"date": "2024-05-20", "open": 22.34, "high": 24.24, "low": 18.95, "close": 22.74, "volume": 2815730, "ema20": 21.7066, "sma50": 15.0998, "sma200": 15.4905}, {"date": "2024-05-21", "open": 22.06, "high": 23.0, "low": 20.05, "close": 21.76, "volume": 3373908, "ema20": 21.7117, "sma50": 15.2466, "sma200": 15.4932}, {"date": "2024-05-22", "open": 21.51, "high": 22.57, "low": 20.76, "close": 21.11, "volume": 3731455, "ema20": 21.6544, "sma50": 15.3748, "sma200": 15.4935}, {"date": "2024-05-23", "open": 21.05, "high": 21.74, "low": 18.15, "close": 18.28, "volume": 1563425, "ema20": 21.333, "sma50": 15.443, "sma200": 15.4817}, {"date": "2024-05-24", "open": 18.83, "high": 23.68, "low": 17.7, "close": 21.44, "volume": 1756040, "ema20": 21.3432, "sma50": 15.5792, "sma200": 15.4892}, {"date": "2024-05-28", "open": 23.22, "high": 26.62, "low": 21.17, "close": 23.01, "volume": 3132011, "ema20": 21.5019, "sma50": 15.7542, "sma200": 15.5033}, {"date": "2024-05-29", "open": 22.7, "high": 22.9, "low": 20.61, "close": 20.86, "volume": 948506, "ema20": 21.4408, "sma50": 15.8934, "sma200": 15.5078}, {"date": "2024-05-30", "open": 20.81, "high": 22.7, "low": 20.11, "close": 22.26, "volume": 607287, "ema20": 21.5188, "sma50": 16.07, "sma200": 15.5194}, {"date": "2024-05-31", "open": 22.1, "high": 23.72, "low": 21.7, "close": 22.97, "volume": 762365, "ema20": 21.657, "sma50": 16.2594, "sma200": 15.5376}, {"date": "2024-06-03", "open": 42.83, "high": 46.81, "low": 26.41, "close": 30.36, "volume": 4592684, "ema20": 22.4859, "sma50": 16.5916, "sma200": 15.5952}, {"date": "2024-06-04", "open": 27.56, "high": 28.01, "low": 25.2, "close": 26.69, "volume": 1747262, "ema20": 22.8863, "sma50": 16.8622, "sma200": 15.6372}, {"date": "2024-06-05", "open": 26.6, "high": 32.9, "low": 26.12, "close": 32.18, "volume": 2309368, "ema20": 23.7714, "sma50": 17.1962, "sma200": 15.7063}, {"date": "2024-06-06", "open": 31.2, "high": 67.5, "low": 30.95, "close": 61.2, "volume": 7623969, "ema20": 27.336, "sma50": 18.1588, "sma200": 15.9198}, {"date": "2024-06-07", "open": 43.89, "high": 48.75, "low": 26.13, "close": 27.15, "volume": 12123697, "ema20": 27.3183, "sma50": 18.4394, "sma200": 15.9694}, {"date": "2024-06-10", "open": 30.35, "high": 31.0, "low": 23.06, "close": 24.98, "volume": 7408357, "ema20": 27.0956, "sma50": 18.688, "sma200": 16.0095}, {"date": "2024-06-11", "open": 24.2, "high": 32.33, "low": 22.79, "close": 29.76, "volume": 6121310, "ema20": 27.3494, "sma50": 19.0422, "sma200": 16.0763}, {"date": "2024-06-12", "open": 29.25, "high": 33.69, "low": 24.81, "close": 26.0, "volume": 4252608, "ema20": 27.2208, "sma50": 19.3362, "sma200": 16.1206}, {"date": "2024-06-13", "open": 26.04, "high": 30.84, "low": 25.56, "close": 28.31, "volume": 3097914, "ema20": 27.3246, "sma50": 19.6736, "sma200": 16.1743}, {"date": "2024-06-14", "open": 28.37, "high": 30.65, "low": 27.41, "close": 28.48, "volume": 2631254, "ema20": 27.4346, "sma50": 20.0136, "sma200": 16.2249}, {"date": "2024-06-17", "open": 28.93, "high": 29.18, "low": 23.78, "close": 25.0, "volume": 2457932, "ema20": 27.2027, "sma50": 20.2886, "sma200": 16.2579}, {"date": "2024-06-18", "open": 24.8, "high": 25.97, "low": 23.61, "close": 24.58, "volume": 1101551, "ema20": 26.953, "sma50": 20.5624, "sma200": 16.288}, {"date": "2024-06-20", "open": 24.32, "high": 25.91, "low": 23.66, "close": 25.28, "volume": 1084484, "ema20": 26.7936, "sma50": 20.845, "sma200": 16.3224}, {"date": "2024-06-21", "open": 25.17, "high": 25.8, "low": 23.54, "close": 23.85, "volume": 943252, "ema20": 26.5133, "sma50": 21.105, "sma200": 16.3452}, {"date": "2024-06-24", "open": 23.01, "high": 24.82, "low": 22.88, "close": 23.48, "volume": 809254, "ema20": 26.2244, "sma50": 21.3488, "sma200": 16.3653}, {"date": "2024-06-25", "open": 23.58, "high": 25.0, "low": 22.56, "close": 24.67, "volume": 906695, "ema20": 26.0764, "sma50": 21.6262, "sma200": 16.3973}, {"date": "2024-06-26", "open": 24.42, "high": 25.38, "low": 23.96, "close": 24.02, "volume": 716147, "ema20": 25.8805, "sma50": 21.9056, "sma200": 16.4291}, {"date": "2024-06-27", "open": 24.1, "high": 26.67, "low": 24.03, "close": 24.96, "volume": 1514767, "ema20": 25.7929, "sma50": 22.1972, "sma200": 16.4659}, {"date": "2024-06-28", "open": 25.25, "high": 26.16, "low": 24.32, "close": 24.8, "volume": 940172, "ema20": 25.6983, "sma50": 22.4868, "sma200": 16.5034}, {"date": "2024-07-01", "open": 23.55, "high": 23.77, "low": 22.32, "close": 23.31, "volume": 1363747, "ema20": 25.4708, "sma50": 22.7464, "sma200": 16.5309}, {"date": "2024-07-02", "open": 23.15, "high": 24.31, "low": 22.9, "close": 23.87, "volume": 550209, "ema20": 25.3184, "sma50": 23.0156, "sma200": 16.5585}, {"date": "2024-07-03", "open": 23.9, "high": 24.89, "low": 23.65, "close": 24.45, "volume": 491920, "ema20": 25.2357, "sma50": 23.3046, "sma200": 16.5898}, {"date": "2024-07-05", "open": 24.19, "high": 25.06, "low": 23.83, "close": 24.11, "volume": 538151, "ema20": 25.1285, "sma50": 23.5834, "sma200": 16.6225}, {"date": "2024-07-08", "open": 24.21, "high": 25.13, "low": 23.86, "close": 24.45, "volume": 496536, "ema20": 25.0639, "sma50": 23.8574, "sma200": 16.6571}, {"date": "2024-07-09", "open": 24.55, "high": 25.15, "low": 24.01, "close": 24.68, "volume": 404787, "ema20": 25.0273, "sma50": 24.1288, "sma200": 16.6933}, {"date": "2024-07-10", "open": 24.72, "high": 26.45, "low": 24.7, "close": 25.06, "volume": 1033234, "ema20": 25.0304, "sma50": 24.3948, "sma200": 16.7336}, {"date": "2024-07-11", "open": 25.32, "high": 26.01, "low": 25.03, "close": 25.36, "volume": 557433, "ema20": 25.0618, "sma50": 24.6768, "sma200": 16.7745}, {"date": "2024-07-12", "open": 25.53, "high": 26.88, "low": 25.42, "close": 26.19, "volume": 719306, "ema20": 25.1692, "sma50": 24.9788, "sma200": 16.8181}, {"date": "2024-07-15", "open": 25.75, "high": 27.19, "low": 25.66, "close": 26.9, "volume": 709901, "ema20": 25.3341, "sma50": 25.2962, "sma200": 16.8681}, {"date": "2024-07-16", "open": 27.2, "high": 29.99, "low": 27.13, "close": 29.63, "volume": 1022689, "ema20": 25.7432, "sma50": 25.6372, "sma200": 16.9309}, {"date": "2024-07-17", "open": 29.02, "high": 29.79, "low": 27.1, "close": 27.81, "volume": 1063746, "ema20": 25.9401, "sma50": 25.8714, "sma200": 16.9858}, {"date": "2024-07-18", "open": 27.83, "high": 28.37, "low": 25.61, "close": 26.06, "volume": 776089, "ema20": 25.9515, "sma50": 26.0726, "sma200": 17.0336}, {"date": "2024-07-19", "open": 25.52, "high": 26.39, "low": 24.85, "close": 24.91, "volume": 779222, "ema20": 25.8523, "sma50": 26.2498, "sma200": 17.0811}, {"date": "2024-07-22", "open": 24.44, "high": 25.98, "low": 24.35, "close": 25.09, "volume": 568838, "ema20": 25.7797, "sma50": 26.4326, "sma200": 17.1336}, {"date": "2024-07-23", "open": 25.05, "high": 25.67, "low": 24.89, "close": 25.2, "volume": 309740, "ema20": 25.7245, "sma50": 26.5652, "sma200": 17.1854}, {"date": "2024-07-24", "open": 25.23, "high": 25.45, "low": 23.89, "close": 24.0, "volume": 408930, "ema20": 25.5602, "sma50": 26.6982, "sma200": 17.2319}, {"date": "2024-07-25", "open": 23.67, "high": 24.59, "low": 23.37, "close": 23.9, "volume": 345362, "ema20": 25.4021, "sma50": 26.438, "sma200": 17.276}]}